<?xml version="1.0" encoding="UTF-8"?>
<MF0 version="1.1" packageUris="http://schema.mathworks.com/mf0/sl_modelref_info/R2019a">
  <ModelRefInfoRepo.ModelRefInfoRoot type="ModelRefInfoRepo.ModelRefInfoRoot" uuid="e682133e-76c1-42f9-89b8-8db16cda2052">
    <autoSolverStatusFlags>331</autoSolverStatusFlags>
    <childModelRefInfo type="ModelRefInfoRepo.ChildModelRefInfo" uuid="8036ed69-829e-4606-94f7-4059b97a419c">
      <modelName>ex_codegen_dsp</modelName>
      <modelPath>ex_codegen_dsp</modelPath>
    </childModelRefInfo>
    <dataTransferInfos>AAFJTQAAAAAOAAAAOAAAAAYAAAAIAAAAAgAAAAAAAAAFAAAACAAAAAAAAAABAAAAAQAAAAAAAAAFAAQAAQAAAAEAAAAAAAAA</dataTransferInfos>
    <fundamentalSampleTimePeriod>0.050000000000000003</fundamentalSampleTimePeriod>
    <hasBlockWithPeriodicDiscreteSampleTime>true</hasBlockWithPeriodicDiscreteSampleTime>
    <hasBwsAccessed>true</hasBwsAccessed>
    <hasBwsAccessedByAnyModel>true</hasBwsAccessedByAnyModel>
    <loggingSaveFormat>4</loggingSaveFormat>
    <maxFreqHz>0.5</maxFreqHz>
    <runtimeNonFcnCallRateInfos type="ModelRefInfoRepo.RateInfo">
      <compiled>true</compiled>
      <nonFcnCallPartitionName>D1</nonFcnCallPartitionName>
      <period>0.050000000000000003</period>
      <priority>40</priority>
      <rateIdx>0</rateIdx>
    </runtimeNonFcnCallRateInfos>
    <sampleTimeInheritanceRule>2</sampleTimeInheritanceRule>
    <timingAndTaskingRegistry>&lt;?xml version=&quot;1.0&quot;?&gt;
&lt;slexec_sto version=&quot;1.1&quot; packageUris=&quot;http://schema.mathworks.com/mf0/slexec_mm_sto/R2019a_201808021136&quot;&gt;
  &lt;sto.Registry type=&quot;sto.Registry&quot; uuid=&quot;ce7589bd-9fb7-4ffd-bb83-da20b4934bfb&quot;&gt;
    &lt;clocks type=&quot;sto.Timer&quot; uuid=&quot;e9406fd3-6443-450f-a232-a143afb0d2ea&quot;&gt;
      &lt;needsToProvideTimeDuringExecution&gt;true&lt;/needsToProvideTimeDuringExecution&gt;
      &lt;clockTickConstraint&gt;PeriodicWithFixedResolution&lt;/clockTickConstraint&gt;
      &lt;resolution&gt;0.050000000000000003&lt;/resolution&gt;
      &lt;clockDomain type=&quot;sto.ClockDomain&quot; uuid=&quot;92cc961c-bbe0-4216-bf81-9e781c23a043&quot;&gt;
        &lt;baseTaskID&gt;_task0&lt;/baseTaskID&gt;
        &lt;computedFundamentalStepSize&gt;0.050000000000000003&lt;/computedFundamentalStepSize&gt;
        &lt;rates type=&quot;sto.Rate&quot; uuid=&quot;318c4cae-5b9c-4bb9-b533-8a115d486efe&quot;/&gt;
        &lt;rates type=&quot;sto.Rate&quot; uuid=&quot;d459cd27-2f86-4163-a286-af37fd753840&quot;/&gt;
        &lt;rootTaskHierarchyElements type=&quot;sto.Task&quot; uuid=&quot;dba77849-f059-443f-8083-b3ca1217be63&quot;&gt;
          &lt;isExecutable&gt;true&lt;/isExecutable&gt;
          &lt;orderIndex&gt;1&lt;/orderIndex&gt;
          &lt;rates type=&quot;sto.Rate&quot; uuid=&quot;318c4cae-5b9c-4bb9-b533-8a115d486efe&quot;&gt;
            &lt;annotation&gt;FiM&lt;/annotation&gt;
            &lt;colorIndex&gt;8&lt;/colorIndex&gt;
            &lt;description&gt;最小ステップに固定&lt;/description&gt;
            &lt;eventSourceType&gt;UNSPECIFIED_EVENT_SOURCE&lt;/eventSourceType&gt;
            &lt;rateIDX&gt;-1&lt;/rateIDX&gt;
            &lt;registry type=&quot;sto.Registry&quot; uuid=&quot;ce7589bd-9fb7-4ffd-bb83-da20b4934bfb&quot;/&gt;
            &lt;taskId&gt;_task0&lt;/taskId&gt;
            &lt;useForExecution&gt;NotForExecution&lt;/useForExecution&gt;
            &lt;rateSpec type=&quot;sto.RateSpec&quot; uuid=&quot;15574b76-4090-41ca-80c5-d452706e31b2&quot;&gt;
              &lt;offset&gt;1&lt;/offset&gt;
              &lt;rateType&gt;ZOHContinuous&lt;/rateType&gt;
            &lt;/rateSpec&gt;
          &lt;/rates&gt;
          &lt;rates type=&quot;sto.Rate&quot; uuid=&quot;d459cd27-2f86-4163-a286-af37fd753840&quot;&gt;
            &lt;annotation&gt;D1&lt;/annotation&gt;
            &lt;colorIndex&gt;2&lt;/colorIndex&gt;
            &lt;description&gt;離散 1&lt;/description&gt;
            &lt;eventSourceType&gt;UNSPECIFIED_EVENT_SOURCE&lt;/eventSourceType&gt;
            &lt;registry type=&quot;sto.Registry&quot; uuid=&quot;ce7589bd-9fb7-4ffd-bb83-da20b4934bfb&quot;/&gt;
            &lt;taskId&gt;_task0&lt;/taskId&gt;
            &lt;rateSpec type=&quot;sto.RateSpec&quot; uuid=&quot;a5b31c62-c7a8-4eeb-8a53-d4da4c9d69aa&quot;&gt;
              &lt;period&gt;0.050000000000000003&lt;/period&gt;
              &lt;rateType&gt;ClassicPeriodicDiscrete&lt;/rateType&gt;
            &lt;/rateSpec&gt;
          &lt;/rates&gt;
          &lt;elementType&gt;Task&lt;/elementType&gt;
          &lt;identifier&gt;_task0&lt;/identifier&gt;
          &lt;priority&gt;40&lt;/priority&gt;
        &lt;/rootTaskHierarchyElements&gt;
      &lt;/clockDomain&gt;
    &lt;/clocks&gt;
    &lt;executionSpec&gt;Undetermined&lt;/executionSpec&gt;
    &lt;taskDependencyGraph type=&quot;sto.SerializedTaskConnectionList&quot; uuid=&quot;759fc4a4-a6a0-46a2-bcbb-4fa06d78c9f9&quot;&gt;
      &lt;taskIdentifier&gt;_task0&lt;/taskIdentifier&gt;
    &lt;/taskDependencyGraph&gt;
    &lt;taskPriorityDirection&gt;HighNumberLast&lt;/taskPriorityDirection&gt;
    &lt;tasks type=&quot;sto.Task&quot; uuid=&quot;dba77849-f059-443f-8083-b3ca1217be63&quot;/&gt;
  &lt;/sto.Registry&gt;
&lt;/slexec_sto&gt;</timingAndTaskingRegistry>
    <FMUBlockMap type="ModelRefInfoRepo.FMUBlockInfo" uuid="d432c053-4ad9-446a-8c19-c6066f703109"/>
    <codeGenInfo type="ModelRefInfoRepo.CodeGenInformation" uuid="a3673fc7-718a-4bac-807d-b70bd96c4826"/>
    <configSettingsForConsistencyChecks type="ModelRefInfoRepo.ConfigSettingsForConsistencyChecks" uuid="d622df0b-4ba6-4641-be5f-39b7a32e3eb3">
      <fixedStepSize>0.050000000000000003</fixedStepSize>
      <frameDiagnosticSetting>2</frameDiagnosticSetting>
      <hasHybridSampleTime>true</hasHybridSampleTime>
      <signalLoggingSaveFormat>2</signalLoggingSaveFormat>
      <solverName>FixedStepDiscrete</solverName>
      <solverType>SOLVER_TYPE_FIXEDSTEP</solverType>
      <hardwareSettings type="ModelRefInfoRepo.HardwareSettings" uuid="370b3e60-19ce-4ed8-9ff2-d90f2080976b">
        <prodBitPerChar>8</prodBitPerChar>
        <prodBitPerDouble>64</prodBitPerDouble>
        <prodBitPerFloat>32</prodBitPerFloat>
        <prodBitPerInt>32</prodBitPerInt>
        <prodBitPerLong>32</prodBitPerLong>
        <prodBitPerLongLong>64</prodBitPerLongLong>
        <prodBitPerPointer>32</prodBitPerPointer>
        <prodBitPerPtrDiffT>32</prodBitPerPtrDiffT>
        <prodBitPerShort>16</prodBitPerShort>
        <prodBitPerSizeT>32</prodBitPerSizeT>
        <prodIntDivRoundTo>2</prodIntDivRoundTo>
        <prodLargestAtomicFloat>2</prodLargestAtomicFloat>
        <prodShiftRight>true</prodShiftRight>
        <prodWordSize>32</prodWordSize>
      </hardwareSettings>
    </configSettingsForConsistencyChecks>
    <dataPortGroup type="ModelRefInfoRepo.DataPortGroup" uuid="19553099-f42c-4c90-bd3b-37e66b2f1d7a"/>
    <interfaceParameterInfo type="ModelRefInfoRepo.InterfaceParameterInfo" uuid="c1377899-3a03-4138-b8df-ca05a44c05c6"/>
    <messageInfo type="ModelRefInfoRepo.MessageInformation" uuid="7dfc0f3e-f095-463c-b8c3-425f503709df"/>
    <methodInfo type="ModelRefInfoRepo.MethodExistenceInfo" uuid="4cc64392-66a0-4c91-8adf-22db39a7a2cb">
      <hasSystemInitializeMethod>true</hasSystemInitializeMethod>
      <hasSystemResetMethod>true</hasSystemResetMethod>
      <hasTerminateMethod>true</hasTerminateMethod>
    </methodInfo>
    <periodicEventPortUnsupportedBlockInfo type="ModelRefInfoRepo.PeriodicEventPortUnsupportedBlockInfo" uuid="3c4f262e-8871-4905-b19d-3258d8ec7d17"/>
    <portGroupsRequireSameRate type="ModelRefInfoRepo.PortGroupsRequireSameRate" uuid="b33a2bb7-7d1d-41b8-abb2-7fbf8a698e14">
      <DSMPortGroups type="ModelRefInfoRepo.NameToPortGroupIdxVectMap" uuid="d918fe82-cdc6-4599-80d2-4ea3133ec2d2"/>
      <GlobalDSMPortGroups type="ModelRefInfoRepo.NameToPortGroupIdxVectMap" uuid="bbba7d89-d8d2-41d0-b1d5-9e4262a57d23"/>
      <mergedPortGroups type="ModelRefInfoRepo.NameToPortGroupIdxVectMap" uuid="5ad5e747-a7e1-4924-aaf8-7dc33a911d9c"/>
    </portGroupsRequireSameRate>
    <rateSpecOfGlobalDSMAccessedByDescExpFcnMdlMap type="ModelRefInfoRepo.GlobalDSMRateSpecMap" uuid="bf6aa39d-863c-41cc-a019-86edbc71e521"/>
    <simulinkFunctions type="ModelRefInfoRepo.SimulinkFunctions" uuid="c58c570f-892a-40d5-9ca5-3bd688e42a3d">
      <compSimulinkFunctionCatalog></compSimulinkFunctionCatalog>
      <variantSimulinkFunctions type="ModelRefInfoRepo.VariantSimulinkFunctions" uuid="17978f8c-db58-41e0-9fe6-036aa550bc0b"/>
    </simulinkFunctions>
    <stateWriterToOwnerMap type="ModelRefInfoRepo.StateWriterInfo" uuid="1e8d09b3-3dcd-408a-badf-10cce22ca7b5"/>
  </ModelRefInfoRepo.ModelRefInfoRoot>
</MF0>